mmh3.cpython-38-x86_64-linux-gnu.so
mmh3/__init__.pyi
mmh3/murmurhash3.c
mmh3/mmh3module.c
mmh3/murmurhash3.h
mmh3/hashlib.h
mmh3/py.typed
mmh3-5.0.1.dist-info/LICENSE
mmh3-5.0.1.dist-info/METADATA
mmh3-5.0.1.dist-info/RECORD
mmh3-5.0.1.dist-info/WHEEL
mmh3-5.0.1.dist-info/top_level.txt
