Metadata-Version: 2.1
Name: mmh3
Version: 5.0.1
Summary: Python extension for MurmurHash (MurmurHash3), a set of fast and robust hash functions.
Author-email: Hajime Senuma <hajime.senuma@gmail.com>
License: MIT License
Project-URL: Homepage, https://pypi.org/project/mmh3/
Project-URL: Repository, https://github.com/hajimes/mmh3
Project-URL: Changelog, https://github.com/hajimes/mmh3/blob/master/CHANGELOG.md
Project-URL: Bug Tracker, https://github.com/hajimes/mmh3/issues
Keywords: utility,hash,MurmurHash
Classifier: Development Status :: 5 - Production/Stable
Classifier: Intended Audience :: Developers
Classifier: License :: OSI Approved :: MIT License
Classifier: Programming Language :: Python :: 3
Classifier: Programming Language :: Python :: 3.8
Classifier: Programming Language :: Python :: 3.9
Classifier: Programming Language :: Python :: 3.10
Classifier: Programming Language :: Python :: 3.11
Classifier: Programming Language :: Python :: 3.12
Classifier: Programming Language :: Python :: 3.13
Classifier: Topic :: Software Development :: Libraries
Classifier: Topic :: Utilities
Requires-Python: >=3.8
License-File: LICENSE
Provides-Extra: test
Requires-Dist: pytest==8.3.3; extra == "test"
Requires-Dist: pytest-sugar==1.0.0; extra == "test"
Provides-Extra: lint
Requires-Dist: black==24.8.0; extra == "lint"
Requires-Dist: clang-format==18.1.8; extra == "lint"
Requires-Dist: isort==5.13.2; extra == "lint"
Requires-Dist: pylint==3.2.7; extra == "lint"
Provides-Extra: type
Requires-Dist: mypy==1.11.2; extra == "type"
Provides-Extra: docs
Requires-Dist: myst-parser==4.0.0; extra == "docs"
Requires-Dist: shibuya==2024.8.30; extra == "docs"
Requires-Dist: sphinx==8.0.2; extra == "docs"
Requires-Dist: sphinx-copybutton==0.5.2; extra == "docs"
Provides-Extra: benchmark
Requires-Dist: pymmh3==0.0.5; extra == "benchmark"
Requires-Dist: pyperf==2.7.0; extra == "benchmark"
Requires-Dist: xxhash==3.5.0; extra == "benchmark"
Provides-Extra: plot
Requires-Dist: matplotlib==3.9.2; extra == "plot"
Requires-Dist: pandas==2.2.2; extra == "plot"
